honeypoke_extractor-0.4.3.dist-info/METADATA
honeypoke_extractor-0.4.3.dist-info/WHEEL
honeypoke_extractor-0.4.3.dist-info/entry_points.txt
honeypoke_extractor-0.4.3.dist-info/licenses/LICENSE
honeypoke_extractor/__init__.py
honeypoke_extractor/base.py
honeypoke_extractor/detect/__init__.py
honeypoke_extractor/detect/cmd_check.py
honeypoke_extractor/detect/ids.py
honeypoke_extractor/detect/portpattern.py
honeypoke_extractor/enrichment/address/__init__.py
honeypoke_extractor/enrichment/port/__init__.py
honeypoke_extractor-0.4.3.dist-info/RECORD
