Metadata-Version: 2.1
Name: honeypoke-extractor
Version: 0.4.3
Summary: Library for extracting and enriching data from HoneyPoke ElasticSearch instances.
Author-Email: Jacob Hartman <jacob@j2h2.com>
Maintainer-Email: Jacob Hartman <jacob@j2h2.com>
License: MIT License
Classifier: Development Status :: 3 - Alpha
Classifier: Intended Audience :: Developers
Classifier: Topic :: Software Development :: Build Tools
Classifier: License :: OSI Approved :: MIT License
Classifier: Programming Language :: Python :: 3
Classifier: Programming Language :: Python :: 3.8
Classifier: Programming Language :: Python :: 3.9
Classifier: Programming Language :: Python :: 3.10
Classifier: Programming Language :: Python :: 3.11
Project-URL: Homepage, https://github.com/bocajspear1/honeypoke-extractor
Project-URL: Repository, https://github.com/bocajspear1/honeypoke-extractor
Project-URL: Issues, https://github.com/bocajspear1/honeypoke-extractor/issues
Requires-Python: >=3.8
Requires-Dist: requests==2.31.0
Requires-Dist: elasticsearch==8.11.1
Requires-Dist: suricataparser==1.0.0
Requires-Dist: regex==2024.5.15
Requires-Dist: importlib-metadata; python_version < "3.8"
Requires-Dist: dpkt>=1.9.8
